dsms/__init__.py
dsms/apps/__init__.py
dsms/apps/config.py
dsms/apps/utils.py
dsms/core/__init__.py
dsms/core/configuration.py
dsms/core/dsms.py
dsms/core/logging.py
dsms/core/session.py
dsms/core/utils.py
dsms/knowledge/__init__.py
dsms/knowledge/cli.py
dsms/knowledge/compacted.py
dsms/knowledge/kitem.py
dsms/knowledge/ktype.py
dsms/knowledge/search.py
dsms/knowledge/utils.py
dsms/knowledge/webform.py
dsms/knowledge/properties/__init__.py
dsms/knowledge/properties/affiliations.py
dsms/knowledge/properties/annotations.py
dsms/knowledge/properties/apps.py
dsms/knowledge/properties/attachments.py
dsms/knowledge/properties/authors.py
dsms/knowledge/properties/avatar.py
dsms/knowledge/properties/contacts.py
dsms/knowledge/properties/dataframe.py
dsms/knowledge/properties/external_links.py
dsms/knowledge/properties/linked_kitems.py
dsms/knowledge/properties/summary.py
dsms/knowledge/properties/user_groups.py
dsms/knowledge/properties/utils.py
dsms/knowledge/semantics/__init__.py
dsms/knowledge/semantics/queries/__init__.py
dsms/knowledge/semantics/queries/base.py
dsms/knowledge/semantics/units/__init__.py
dsms/knowledge/semantics/units/base.py
dsms/knowledge/semantics/units/conversion.py
dsms/knowledge/semantics/units/sparql.py
dsms/knowledge/semantics/units/utils.py
dsms/knowledge/sparql_interface/__init__.py
dsms/knowledge/sparql_interface/sparql_interface.py
dsms/knowledge/sparql_interface/subgraph.py
dsms/knowledge/sparql_interface/utils.py
dsms_sdk-4.1.1.dist-info/licenses/LICENSE
tests/__init__.py
tests/conftest.py
tests/test_kitem.py
tests/test_utils.py
dsms_sdk-4.1.1.dist-info/METADATA
dsms_sdk-4.1.1.dist-info/WHEEL
dsms_sdk-4.1.1.dist-info/entry_points.txt
dsms_sdk-4.1.1.dist-info/top_level.txt
dsms_sdk-4.1.1.dist-info/RECORD
