Metadata-Version: 2.4
Name: dsms_sdk
Version: 4.1.1
Summary: Python SDK core-package for working with the Dataspace Management System (DSMS).
Home-page: https://github.com/MI-FraunhoferIWM/dsms-python-sdk
Author: Matthias Büschelberger, Yoav Nahshon, Pablo De Andres, Arjun Gopalakrishnan, Priyabrat Mishra
Author-email: matthias.bueschelberger@iwm.fraunhofer.de, yoav.nahshon@iwm.fraunhofer.de, arjun.gopalakrishnan@iwm.fraunhofer.de, priyabrat.mishra@iwm.fraunhofer.de
License: BSD-3-Clause
Classifier: Development Status :: 2 - Pre-Alpha
Classifier: License :: OSI Approved :: BSD License
Classifier: Programming Language :: Python :: 3
Classifier: Programming Language :: Python :: 3 :: Only
Classifier: Programming Language :: Python :: Implementation :: CPython
Requires-Python: >=3.8
License-File: LICENSE
Requires-Dist: PyYAML<7,>=6
Requires-Dist: click<9,>=8
Requires-Dist: html5lib<2,>=1
Requires-Dist: lru-cache<1
Requires-Dist: oyaml==1
Requires-Dist: pandas<3,>=2
Requires-Dist: pydantic<=2.11.7,>=2
Requires-Dist: pydantic-settings
Requires-Dist: python-dotenv
Requires-Dist: qrcode-artistic<4,>=3
Requires-Dist: rdflib<7,>=6
Requires-Dist: requests
Requires-Dist: segno<1.7,>=1.6
Provides-Extra: dev
Requires-Dist: bumpver==2021.1114; extra == "dev"
Requires-Dist: dunamai==1.7.0; extra == "dev"
Provides-Extra: docs
Requires-Dist: ipython==8.26.0; extra == "docs"
Requires-Dist: jupyter==1.0.0; extra == "docs"
Requires-Dist: myst-parser==4.0.0; extra == "docs"
Requires-Dist: nbsphinx==0.9.5; extra == "docs"
Requires-Dist: sphinx-autobuild==2024.4.16; extra == "docs"
Requires-Dist: sphinx-book-theme==1.1.3; extra == "docs"
Requires-Dist: sphinx-copybutton==0.5.2; extra == "docs"
Requires-Dist: sphinx-markdown-tables==0.0.17; extra == "docs"
Requires-Dist: sphinx-panels==0.4.1; extra == "docs"
Requires-Dist: sphinxcontrib-plantuml==0.30; extra == "docs"
Requires-Dist: sphinxcontrib-redoc==1.6.0; extra == "docs"
Provides-Extra: pre-commit
Requires-Dist: pre-commit==3.3.2; extra == "pre-commit"
Requires-Dist: pylint==3.2.0; extra == "pre-commit"
Provides-Extra: tests
Requires-Dist: pytest>=7.4.3; extra == "tests"
Requires-Dist: pytest-mock; extra == "tests"
Requires-Dist: responses; extra == "tests"
Dynamic: license-file
